MANIFEST.in
README.txt
bootstrap.py
buildout.cfg
setup.cfg
setup.py
docs/Makefile
docs/conf.py
docs/index.rst
docs/make.bat
docs/sphinx-sample.jpg
docs/sphinxusers.jpg
src/AUTHORS.txt
src/HISTORY.txt
src/LICENSE.txt
src/README.txt
src/TODOS.txt
src/sphinxjp/__init__.py
src/sphinxjp.themes.s6.egg-info/PKG-INFO
src/sphinxjp.themes.s6.egg-info/SOURCES.txt
src/sphinxjp.themes.s6.egg-info/dependency_links.txt
src/sphinxjp.themes.s6.egg-info/entry_points.txt
src/sphinxjp.themes.s6.egg-info/namespace_packages.txt
src/sphinxjp.themes.s6.egg-info/not-zip-safe
src/sphinxjp.themes.s6.egg-info/requires.txt
src/sphinxjp.themes.s6.egg-info/top_level.txt
src/sphinxjp/themes/__init__.py
src/sphinxjp/themes/s6/__init__.py
src/sphinxjp/themes/s6/directives.py
src/sphinxjp/themes/s6/templates/s6/AUTHORS.txt
src/sphinxjp/themes/s6/templates/s6/LICENSE.txt
src/sphinxjp/themes/s6/templates/s6/layout.html
src/sphinxjp/themes/s6/templates/s6/theme.conf
src/sphinxjp/themes/s6/templates/s6/static/background.png
src/sphinxjp/themes/s6/templates/s6/static/bg_t.gif
src/sphinxjp/themes/s6/templates/s6/static/jquery.js
src/sphinxjp/themes/s6/templates/s6/static/jquery.touchwipe.min.js
src/sphinxjp/themes/s6/templates/s6/static/s6-sphinx.js
src/sphinxjp/themes/s6/templates/s6/static/s6.css
src/sphinxjp/themes/s6/templates/s6/static/s6.js
src/sphinxjp/themes/s6/templates/s6/static/title_bg.gif