Metadata-Version: 1.0
Name: sphinxjp.themes.s6
Version: 0.3.0
Summary: A sphinx theme for generate S6 presentation. #sphinxjp
Home-page: http://bitbucket.org/shimizukawa/sphinxjp.themes.s6
Author: Takayuki SHIMIZUKAWA
Author-email: shimizukawa at gmail dot com
License: MIT
Keywords: sphinx,reStructuredText,presentation
Platform: UNKNOWN
Classifier: Development Status :: 4 - Beta
Classifier: License :: OSI Approved :: MIT License
Classifier: Programming Language :: Python
Classifier: Programming Language :: Python :: 2
Classifier: Programming Language :: Python :: 3
Classifier: Topic :: Software Development
Classifier: Topic :: Software Development :: Documentation
Classifier: Topic :: Text Processing :: Markup
